spatialim-2.1.0.dist-info/METADATA
spatialim-2.1.0.dist-info/WHEEL
spatialim/__init__.py
spatialim/_spatialim.pyi
spatialim/plotting.py
spatialim-2.1.0.dist-info/RECORD
