Metadata-Version: 2.4
Name: spatialim
Version: 2.1.0
Classifier: Programming Language :: Rust
Classifier: Programming Language :: Python :: Implementation :: CPython
Classifier: Programming Language :: Python :: Implementation :: PyPy
Requires-Dist: matplotlib
Requires-Dist: scipy
Requires-Dist: pandas
Summary: Spatial seismic intensity simulation library
Keywords: earthquake,seismic,simulation,spatial,intensity
Author-email: Tian You <youtian@njtech.edu.cn>
License-Expression: GPL-3.0-or-later
Requires-Python: >=3.7
Project-URL: Homepage, https://github.com/youtian95/spatialim
Project-URL: Documentation, https://github.com/youtian95/spatialim/blob/rust/README.md
Project-URL: Repository, https://github.com/youtian95/spatialim.git
Project-URL: Changelog, https://github.com/youtian95/spatialim/blob/rust/CHANGELOG.md
